objaverse/__init__.py
objaverse/utils.py
objaverse/xl/__init__.py
objaverse/xl/abstract.py
objaverse/xl/github.py
objaverse/xl/sketchfab.py
objaverse/xl/smithsonian.py
objaverse/xl/thingiverse.py
objaverse-0.1.7.dist-info/LICENSE
objaverse-0.1.7.dist-info/METADATA
objaverse-0.1.7.dist-info/WHEEL
objaverse-0.1.7.dist-info/top_level.txt
objaverse-0.1.7.dist-info/RECORD
